inputkit/Getch.py
inputkit/__init__.py
inputkit/inputlib.py
inputkit/inputs.py
inputkit/inputstools.py
inputkit/pyg.py
inputkit-0.2.0.dist-info/LICENCE.txt
inputkit-0.2.0.dist-info/METADATA
inputkit-0.2.0.dist-info/WHEEL
inputkit-0.2.0.dist-info/top_level.txt
inputkit-0.2.0.dist-info/RECORD
