Metadata-Version: 2.1
Name: inputkit
Version: 0.2.0
Summary: library of input functions. and an input API
Home-page: 
Author: Alawi Hussein Adnan Al Sayegh
Author-email: programming.laboratorys@gmail.com
License: MIT
Keywords: inputs,inputing,inputed,input,inputtools,tools,toolkit,tooling,useful_input,useful
Classifier: Development Status :: 5 - Production/Stable
Classifier: Intended Audience :: Developers
Classifier: Operating System :: Microsoft :: Windows :: Windows 10
Classifier: Operating System :: Microsoft :: Windows
Classifier: Operating System :: POSIX :: Linux
Classifier: Intended Audience :: Developers
Classifier: Programming Language :: Python :: 3
Classifier: License :: OSI Approved :: MIT License
License-File: LICENCE.txt
